fanesis/__init__.py
fanesis/grouping.py
fanesis/individualize.py
fanesis/pipeline.py
fanesis/utils.py
fanesis/visualize.py
fanesis-0.1.0.dist-info/METADATA
fanesis-0.1.0.dist-info/WHEEL
fanesis-0.1.0.dist-info/RECORD
