Metadata-Version: 2.1
Name: fanesis
Version: 0.1.0
Summary: network analysis tool based on face recognition
Author: Sulthan Abiyyu
Requires-Python: >=3.10,<3.13
Classifier: Programming Language :: Python :: 3
Classifier: Programming Language :: Python :: 3.10
Classifier: Programming Language :: Python :: 3.11
Requires-Dist: deepface (==0.0.79)
Requires-Dist: facenet-pytorch (>=2.5.3,<3.0.0)
Requires-Dist: matplotlib (>=3.8.0,<4.0.0)
Requires-Dist: networkx (>=3.1,<4.0)
Requires-Dist: numpy (>=1.26.0,<2.0.0)
Requires-Dist: pandas (>=2.1.1,<3.0.0)
Requires-Dist: pyvis (>=0.3.2,<0.4.0)
Requires-Dist: scipy (>=1.11.3,<2.0.0)
